odoo10_addon_l10n_fr_hr_check_ssnid-10.0.1.0.0.99.dev7-py2.7-nspkg.pth
odoo/addons/l10n_fr_hr_check_ssnid/README.rst
odoo/addons/l10n_fr_hr_check_ssnid/__init__.py
odoo/addons/l10n_fr_hr_check_ssnid/__manifest__.py
odoo/addons/l10n_fr_hr_check_ssnid/i18n/fr.po
odoo/addons/l10n_fr_hr_check_ssnid/i18n/l10n_fr_hr_check_ssnid.pot
odoo/addons/l10n_fr_hr_check_ssnid/models/__init__.py
odoo/addons/l10n_fr_hr_check_ssnid/models/hr_employee.py
odoo/addons/l10n_fr_hr_check_ssnid/static/description/icon.png
odoo/addons/l10n_fr_hr_check_ssnid/tests/__init__.py
odoo/addons/l10n_fr_hr_check_ssnid/tests/test_ssnid.py
odoo/addons/l10n_fr_hr_check_ssnid/views/hr_employee.xml
odoo10_addon_l10n_fr_hr_check_ssnid-10.0.1.0.0.99.dev7.dist-info/METADATA
odoo10_addon_l10n_fr_hr_check_ssnid-10.0.1.0.0.99.dev7.dist-info/RECORD
odoo10_addon_l10n_fr_hr_check_ssnid-10.0.1.0.0.99.dev7.dist-info/WHEEL
odoo10_addon_l10n_fr_hr_check_ssnid-10.0.1.0.0.99.dev7.dist-info/namespace_packages.txt
odoo10_addon_l10n_fr_hr_check_ssnid-10.0.1.0.0.99.dev7.dist-info/top_level.txt
