Metadata-Version: 2.1
Name: odoo10-addon-l10n-fr-hr-check-ssnid
Version: 10.0.1.0.0.99.dev7
Summary: Check validity of Social Security Numbers in French companies
Home-page: http://www.akretion.com
Author: Akretion,Odoo Community Association (OCA)
Author-email: support@odoo-community.org
License: AGPL-3
Platform: UNKNOWN
Classifier: Programming Language :: Python
Classifier: Framework :: Odoo
Classifier: License :: OSI Approved :: GNU Affero General Public License v3
Requires-Python: ~=2.7
Requires-Dist: odoo (<10.1dev,>=10.0)
Requires-Dist: python-stdnum
